cookiecutter_nc_demo1/__init__.py
cookiecutter_nc_demo1/common.py
cookiecutter_nc_demo1/cookiecutter_nc_demo1.py
cookiecutter_nc_demo1-0.0.1.dist-info/LICENSE
cookiecutter_nc_demo1-0.0.1.dist-info/METADATA
cookiecutter_nc_demo1-0.0.1.dist-info/WHEEL
cookiecutter_nc_demo1-0.0.1.dist-info/entry_points.txt
cookiecutter_nc_demo1-0.0.1.dist-info/top_level.txt
cookiecutter_nc_demo1-0.0.1.dist-info/RECORD
