Metadata-Version: 2.1
Name: cookiecutter-nc-demo1
Version: 0.0.1
Summary: sample cookiecutte demo project
Author-email: nirnab chowdhury <nirnab06@gmail.com>
License: MIT License
Project-URL: Homepage, https://github.com/nirnab06/cookiecutter-nc-demo1
Keywords: cookiecutter-nc-demo1
Classifier: Intended Audience :: Developers
Classifier: License :: OSI Approved :: MIT License
Classifier: Natural Language :: English
Classifier: Programming Language :: Python :: 3.8
Classifier: Programming Language :: Python :: 3.9
Classifier: Programming Language :: Python :: 3.10
Classifier: Programming Language :: Python :: 3.11
Classifier: Programming Language :: Python :: 3.12
Requires-Python: >=3.8
License-File: LICENSE
Requires-Dist: numpy
Provides-Extra: all
Requires-Dist: cookiecutter-nc-demo1[extra]; extra == "all"
Provides-Extra: extra
Requires-Dist: pandas; extra == "extra"
